spiralsort/__init__.py
spiralsort/__main__.py
spiralsort/config.py
spiralsort/core.py
spiralsort/io.py
spiralsort/spiralsort_post.py
spiralsort/spiralsort_test.py
spiralsort/utilities.py
spiralsort/utils.py
spiralsort-0.3.1.dist-info/COPYING
spiralsort-0.3.1.dist-info/METADATA
spiralsort-0.3.1.dist-info/WHEEL
spiralsort-0.3.1.dist-info/entry_points.txt
spiralsort-0.3.1.dist-info/top_level.txt
spiralsort-0.3.1.dist-info/RECORD
