Metadata-Version: 2.1
Name: spiralsort
Version: 0.3.1
Summary: A point-cloud spiral-sorting algorithm
Home-page: https://github.com/ThanasisMattas/spiralsort.git
Author: Athanasios Mattas
Author-email: thanasismatt@gmail.com
License: GNU GPL3
Platform: UNKNOWN
Classifier: Programming Language :: Python :: 3
Classifier: Natural Language :: English
Classifier: License :: OSI Approved :: GNU Lesser General Public License v3 or later (LGPLv3+)
Classifier: Operating System :: OS Independent
Requires-Dist: click (>=7.0)
Requires-Dist: numba (>=0.48.0)
Requires-Dist: numpy (>=1.18.0)
Requires-Dist: pandas (>=1.0.1)
Provides-Extra: animation
Requires-Dist: ffmpeg (>=4.2.4) ; extra == 'animation'
Requires-Dist: matplotlib (>=3.1.3) ; extra == 'animation'
Requires-Dist: pillow (>=7.0.0) ; extra == 'animation'
Provides-Extra: test
Requires-Dist: pytest (>=5.4.2) ; extra == 'test'
